[
    {
        "name":  "Frost Prime Set",
        "set_median":  88.0,
        "set_volume":  74,
        "set_max_price":  95,
        "set_min_price":  80,
        "set_pieces_median":  75,
        "set_pieces_volume":  185,
        "benefit":  13.0
    },
    {
        "name":  "Mantis Set",
        "set_median":  15,
        "set_volume":  10,
        "set_max_price":  15,
        "set_min_price":  14,
        "set_pieces_median":  17,
        "set_pieces_volume":  21,
        "benefit":  -2
    },
    {
        "name":  "Hydroid Prime Set",
        "set_median":  90,
        "set_volume":  70,
        "set_max_price":  100,
        "set_min_price":  78,
        "set_pieces_median":  70,
        "set_pieces_volume":  147,
        "benefit":  20
    },
    {
        "name":  "Wolf Sledge Set",
        "set_median":  69,
        "set_volume":  10,
        "set_max_price":  70,
        "set_min_price":  69,
        "set_pieces_median":  74,
        "set_pieces_volume":  29,
        "benefit":  -5
    },
    {
        "name":  "Vasto Prime Set",
        "set_median":  29,
        "set_volume":  25,
        "set_max_price":  30,
        "set_min_price":  23,
        "set_pieces_median":  21,
        "set_pieces_volume":  37,
        "benefit":  8
    },
    {
        "name":  "Zhuge Prime Set",
        "set_median":  50,
        "set_volume":  9,
        "set_max_price":  51,
        "set_min_price":  49,
        "set_pieces_median":  40.5,
        "set_pieces_volume":  31,
        "benefit":  9.5
    },
    {
        "name":  "Dual Kamas Prime Set",
        "set_median":  107.5,
        "set_volume":  7,
        "set_max_price":  110,
        "set_min_price":  100,
        "set_pieces_median":  100,
        "set_pieces_volume":  28,
        "benefit":  7.5
    },
    {
        "name":  "Snipetron Vandal Set",
        "set_median":  40,
        "set_volume":  7,
        "set_max_price":  40,
        "set_min_price":  39,
        "set_pieces_median":  41,
        "set_pieces_volume":  10,
        "benefit":  -1
    },
    {
        "name":  "Destreza Prime Set",
        "set_median":  48,
        "set_volume":  10,
        "set_max_price":  50,
        "set_min_price":  40,
        "set_pieces_median":  45,
        "set_pieces_volume":  32,
        "benefit":  3
    },
    {
        "name":  "Saryn Prime Set",
        "set_median":  99,
        "set_volume":  50,
        "set_max_price":  101,
        "set_min_price":  97,
        "set_pieces_median":  99,
        "set_pieces_volume":  105,
        "benefit":  0
    },
    {
        "name":  "Stradavar Prime Set",
        "set_median":  30.0,
        "set_volume":  10,
        "set_max_price":  32,
        "set_min_price":  29,
        "set_pieces_median":  27.5,
        "set_pieces_volume":  31,
        "benefit":  2.5
    },
    {
        "name":  "Helios Prime Set",
        "set_median":  75,
        "set_volume":  34,
        "set_max_price":  80,
        "set_min_price":  67,
        "set_pieces_median":  59.5,
        "set_pieces_volume":  81,
        "benefit":  15.5
    },
    {
        "name":  "Silva \u0026 Aegis Prime Set",
        "set_median":  45.0,
        "set_volume":  18,
        "set_max_price":  55,
        "set_min_price":  35,
        "set_pieces_median":  36,
        "set_pieces_volume":  20,
        "benefit":  9.0
    },
    {
        "name":  "Kavasa Prime Kubrow Collar Set",
        "set_median":  30,
        "set_volume":  3,
        "set_max_price":  30,
        "set_min_price":  29,
        "set_pieces_median":  26,
        "set_pieces_volume":  10,
        "benefit":  4
    },
    {
        "name":  "Latron Prime Set",
        "set_median":  92,
        "set_volume":  17,
        "set_max_price":  95,
        "set_min_price":  88,
        "set_pieces_median":  76,
        "set_pieces_volume":  79,
        "benefit":  16
    },
    {
        "name":  "Lex Prime Set",
        "set_median":  8.0,
        "set_volume":  27,
        "set_max_price":  10,
        "set_min_price":  5,
        "set_pieces_median":  10,
        "set_pieces_volume":  26,
        "benefit":  -2.0
    },
    {
        "name":  "Odonata Prime Set",
        "set_median":  35,
        "set_volume":  16,
        "set_max_price":  45,
        "set_min_price":  29,
        "set_pieces_median":  40.5,
        "set_pieces_volume":  55,
        "benefit":  -5.5
    },
    {
        "name":  "Vectis Prime Set",
        "set_median":  79,
        "set_volume":  20,
        "set_max_price":  85,
        "set_min_price":  70,
        "set_pieces_median":  56,
        "set_pieces_volume":  123,
        "benefit":  23
    },
    {
        "name":  "Rhino Prime Set",
        "set_median":  60.0,
        "set_volume":  85,
        "set_max_price":  60,
        "set_min_price":  57,
        "set_pieces_median":  39,
        "set_pieces_volume":  323,
        "benefit":  21.0
    },
    {
        "name":  "Sicarus Prime Set",
        "set_median":  44.5,
        "set_volume":  22,
        "set_max_price":  49,
        "set_min_price":  40,
        "set_pieces_median":  31,
        "set_pieces_volume":  70,
        "benefit":  13.5
    },
    {
        "name":  "Scimitar Set",
        "set_median":  15,
        "set_volume":  1,
        "set_max_price":  15,
        "set_min_price":  15,
        "set_pieces_median":  16,
        "set_pieces_volume":  12,
        "benefit":  -1
    },
    {
        "name":  "Braton Prime Set",
        "set_median":  7,
        "set_volume":  38,
        "set_max_price":  9,
        "set_min_price":  5,
        "set_pieces_median":  8,
        "set_pieces_volume":  54,
        "benefit":  -1
    },
    {
        "name":  "Aklex Prime Set",
        "set_median":  60.0,
        "set_volume":  8,
        "set_max_price":  60,
        "set_min_price":  59,
        "set_pieces_median":  63,
        "set_pieces_volume":  18,
        "benefit":  -3.0
    },
    {
        "name":  "Ninkondi Prime Set",
        "set_median":  60.0,
        "set_volume":  8,
        "set_max_price":  74,
        "set_min_price":  50,
        "set_pieces_median":  46,
        "set_pieces_volume":  23,
        "benefit":  14.0
    },
    {
        "name":  "Wukong Prime Set",
        "set_median":  80.0,
        "set_volume":  114,
        "set_max_price":  85,
        "set_min_price":  75,
        "set_pieces_median":  68,
        "set_pieces_volume":  198,
        "benefit":  12.0
    },
    {
        "name":  "Ember Prime Set",
        "set_median":  75,
        "set_volume":  116,
        "set_max_price":  85,
        "set_min_price":  65,
        "set_pieces_median":  57,
        "set_pieces_volume":  292,
        "benefit":  18
    },
    {
        "name":  "Fang Prime Set",
        "set_median":  7,
        "set_volume":  14,
        "set_max_price":  10,
        "set_min_price":  5,
        "set_pieces_median":  13.5,
        "set_pieces_volume":  33,
        "benefit":  -6.5
    },
    {
        "name":  "Mag Prime Set",
        "set_median":  90.0,
        "set_volume":  64,
        "set_max_price":  95,
        "set_min_price":  88,
        "set_pieces_median":  81.5,
        "set_pieces_volume":  143,
        "benefit":  8.5
    },
    {
        "name":  "Euphona Prime Set",
        "set_median":  50.0,
        "set_volume":  8,
        "set_max_price":  50,
        "set_min_price":  48,
        "set_pieces_median":  48.5,
        "set_pieces_volume":  29,
        "benefit":  1.5
    },
    {
        "name":  "Oberon Prime Set",
        "set_median":  80,
        "set_volume":  33,
        "set_max_price":  90,
        "set_min_price":  68,
        "set_pieces_median":  61,
        "set_pieces_volume":  84,
        "benefit":  19
    },
    {
        "name":  "Bo Prime Set",
        "set_median":  70.0,
        "set_volume":  20,
        "set_max_price":  78,
        "set_min_price":  60,
        "set_pieces_median":  60,
        "set_pieces_volume":  50,
        "benefit":  10.0
    },
    {
        "name":  "Boar Prime Set",
        "set_median":  90.0,
        "set_volume":  31,
        "set_max_price":  95,
        "set_min_price":  85,
        "set_pieces_median":  80,
        "set_pieces_volume":  90,
        "benefit":  10.0
    },
    {
        "name":  "Boltor Prime Set",
        "set_median":  47,
        "set_volume":  27,
        "set_max_price":  55,
        "set_min_price":  40,
        "set_pieces_median":  35,
        "set_pieces_volume":  132,
        "benefit":  12
    },
    {
        "name":  "Strun Wraith Set",
        "set_median":  63,
        "set_volume":  11,
        "set_max_price":  80,
        "set_min_price":  50,
        "set_pieces_median":  54.5,
        "set_pieces_volume":  10,
        "benefit":  8.5
    },
    {
        "name":  "Kogake Prime Set",
        "set_median":  95.0,
        "set_volume":  8,
        "set_max_price":  100,
        "set_min_price":  90,
        "set_pieces_median":  72,
        "set_pieces_volume":  37,
        "benefit":  23.0
    },
    {
        "name":  "Lato Vandal Set",
        "set_median":  350.0,
        "set_volume":  12,
        "set_max_price":  390,
        "set_min_price":  300,
        "set_pieces_median":  325,
        "set_pieces_volume":  44,
        "benefit":  25.0
    },
    {
        "name":  "Braton Vandal Set",
        "set_median":  390.0,
        "set_volume":  6,
        "set_max_price":  400,
        "set_min_price":  345,
        "set_pieces_median":  288,
        "set_pieces_volume":  46,
        "benefit":  102.0
    },
    {
        "name":  "Akvasto Prime Set",
        "set_median":  100.0,
        "set_volume":  9,
        "set_max_price":  105,
        "set_min_price":  99,
        "set_pieces_median":  98.5,
        "set_pieces_volume":  16,
        "benefit":  1.5
    },
    {
        "name":  "Furax Wraith Set",
        "set_median":  12,
        "set_volume":  13,
        "set_max_price":  15,
        "set_min_price":  9,
        "set_pieces_median":  15,
        "set_pieces_volume":  25,
        "benefit":  -3
    },
    {
        "name":  "Ankyros Prime Set",
        "set_median":  44.5,
        "set_volume":  16,
        "set_max_price":  55,
        "set_min_price":  35,
        "set_pieces_median":  30,
        "set_pieces_volume":  58,
        "benefit":  14.5
    },
    {
        "name":  "Paris Prime Set",
        "set_median":  7,
        "set_volume":  22,
        "set_max_price":  9,
        "set_min_price":  5,
        "set_pieces_median":  9.5,
        "set_pieces_volume":  54,
        "benefit":  -2.5
    },
    {
        "name":  "Trinity Prime Set",
        "set_median":  65.0,
        "set_volume":  48,
        "set_max_price":  74,
        "set_min_price":  52,
        "set_pieces_median":  47.5,
        "set_pieces_volume":  95,
        "benefit":  17.5
    },
    {
        "name":  "Ballistica Prime Set",
        "set_median":  70,
        "set_volume":  13,
        "set_max_price":  70,
        "set_min_price":  65,
        "set_pieces_median":  45,
        "set_pieces_volume":  38,
        "benefit":  25
    },
    {
        "name":  "Venka Prime Set",
        "set_median":  108.5,
        "set_volume":  13,
        "set_max_price":  115,
        "set_min_price":  100,
        "set_pieces_median":  97,
        "set_pieces_volume":  57,
        "benefit":  11.5
    },
    {
        "name":  "Akbronco Prime Set",
        "set_median":  9.0,
        "set_volume":  12,
        "set_max_price":  10,
        "set_min_price":  8,
        "set_pieces_median":  5,
        "set_pieces_volume":  27,
        "benefit":  4.0
    },
    {
        "name":  "Carrier Prime Set",
        "set_median":  72,
        "set_volume":  32,
        "set_max_price":  78,
        "set_min_price":  65,
        "set_pieces_median":  56,
        "set_pieces_volume":  152,
        "benefit":  16
    },
    {
        "name":  "Dakra Prime Set",
        "set_median":  30,
        "set_volume":  9,
        "set_max_price":  30,
        "set_min_price":  29,
        "set_pieces_median":  29,
        "set_pieces_volume":  29,
        "benefit":  1
    },
    {
        "name":  "Dera Vandal Set",
        "set_median":  39,
        "set_volume":  9,
        "set_max_price":  40,
        "set_min_price":  32,
        "set_pieces_median":  35,
        "set_pieces_volume":  10,
        "benefit":  4
    },
    {
        "name":  "Latron Wraith Set",
        "set_median":  65,
        "set_volume":  8,
        "set_max_price":  70,
        "set_min_price":  60,
        "set_pieces_median":  46,
        "set_pieces_volume":  13,
        "benefit":  19
    },
    {
        "name":  "Twin Vipers Wraith Set",
        "set_median":  60.0,
        "set_volume":  4,
        "set_max_price":  60,
        "set_min_price":  52,
        "set_pieces_median":  45.5,
        "set_pieces_volume":  13,
        "benefit":  14.5
    },
    {
        "name":  "Dethcube Prime Set",
        "set_median":  70,
        "set_volume":  37,
        "set_max_price":  75,
        "set_min_price":  58,
        "set_pieces_median":  55,
        "set_pieces_volume":  90,
        "benefit":  15
    },
    {
        "name":  "Baza Prime Set",
        "set_median":  70,
        "set_volume":  18,
        "set_max_price":  80,
        "set_min_price":  65,
        "set_pieces_median":  57.5,
        "set_pieces_volume":  38,
        "benefit":  12.5
    },
    {
        "name":  "Aksomati Prime Set",
        "set_median":  90,
        "set_volume":  9,
        "set_max_price":  90,
        "set_min_price":  84,
        "set_pieces_median":  64.5,
        "set_pieces_volume":  38,
        "benefit":  25.5
    },
    {
        "name":  "Hikou Prime Set",
        "set_median":  50,
        "set_volume":  13,
        "set_max_price":  60,
        "set_min_price":  30,
        "set_pieces_median":  39,
        "set_pieces_volume":  29,
        "benefit":  11
    },
    {
        "name":  "Reaper Prime Set",
        "set_median":  35,
        "set_volume":  30,
        "set_max_price":  40,
        "set_min_price":  29,
        "set_pieces_median":  27.5,
        "set_pieces_volume":  23,
        "benefit":  7.5
    },
    {
        "name":  "Sybaris Prime Set",
        "set_median":  75.0,
        "set_volume":  14,
        "set_max_price":  89,
        "set_min_price":  70,
        "set_pieces_median":  57.5,
        "set_pieces_volume":  68,
        "benefit":  17.5
    },
    {
        "name":  "Shedu Set",
        "set_median":  38.0,
        "set_volume":  21,
        "set_max_price":  40,
        "set_min_price":  35,
        "set_pieces_median":  36,
        "set_pieces_volume":  113,
        "benefit":  2.0
    },
    {
        "name":  "Redeemer Prime Set",
        "set_median":  45.0,
        "set_volume":  18,
        "set_max_price":  50,
        "set_min_price":  35,
        "set_pieces_median":  40,
        "set_pieces_volume":  28,
        "benefit":  5.0
    },
    {
        "name":  "Orthos Prime Set",
        "set_median":  10.0,
        "set_volume":  46,
        "set_max_price":  12,
        "set_min_price":  6,
        "set_pieces_median":  9,
        "set_pieces_volume":  41,
        "benefit":  1.0
    },
    {
        "name":  "Volt Prime Set",
        "set_median":  80,
        "set_volume":  99,
        "set_max_price":  80,
        "set_min_price":  78,
        "set_pieces_median":  71,
        "set_pieces_volume":  205,
        "benefit":  9
    },
    {
        "name":  "Amesha Set",
        "set_median":  45,
        "set_volume":  1,
        "set_max_price":  45,
        "set_min_price":  45,
        "set_pieces_median":  0,
        "set_pieces_volume":  0,
        "benefit":  45
    },
    {
        "name":  "Elytron Set",
        "set_median":  55,
        "set_volume":  1,
        "set_max_price":  55,
        "set_min_price":  55,
        "set_pieces_median":  24,
        "set_pieces_volume":  2,
        "benefit":  31
    },
    {
        "name":  "Itzal Set",
        "set_median":  37.5,
        "set_volume":  2,
        "set_max_price":  40,
        "set_min_price":  35,
        "set_pieces_median":  0,
        "set_pieces_volume":  0,
        "benefit":  37.5
    },
    {
        "name":  "Tigris Prime Set",
        "set_median":  49,
        "set_volume":  11,
        "set_max_price":  50,
        "set_min_price":  40,
        "set_pieces_median":  41.5,
        "set_pieces_volume":  25,
        "benefit":  7.5
    },
    {
        "name":  "Karak Wraith Set",
        "set_median":  60,
        "set_volume":  7,
        "set_max_price":  69,
        "set_min_price":  50,
        "set_pieces_median":  44,
        "set_pieces_volume":  13,
        "benefit":  16
    },
    {
        "name":  "Fragor Prime Set",
        "set_median":  39,
        "set_volume":  14,
        "set_max_price":  45,
        "set_min_price":  35,
        "set_pieces_median":  30,
        "set_pieces_volume":  41,
        "benefit":  9
    },
    {
        "name":  "Pangolin Prime Set",
        "set_median":  30.0,
        "set_volume":  6,
        "set_max_price":  30,
        "set_min_price":  29,
        "set_pieces_median":  23.5,
        "set_pieces_volume":  15,
        "benefit":  6.5
    },
    {
        "name":  "Titania Prime Set",
        "set_median":  70,
        "set_volume":  94,
        "set_max_price":  72,
        "set_min_price":  68,
        "set_pieces_median":  61,
        "set_pieces_volume":  210,
        "benefit":  9
    },
    {
        "name":  "Centaur Set",
        "set_median":  55,
        "set_volume":  1,
        "set_max_price":  55,
        "set_min_price":  55,
        "set_pieces_median":  35.5,
        "set_pieces_volume":  23,
        "benefit":  19.5
    },
    {
        "name":  "Onorix Set",
        "set_median":  30,
        "set_volume":  3,
        "set_max_price":  40,
        "set_min_price":  30,
        "set_pieces_median":  39,
        "set_pieces_volume":  5,
        "benefit":  -9
    },
    {
        "name":  "Agkuza Set",
        "set_median":  44.5,
        "set_volume":  2,
        "set_max_price":  49,
        "set_min_price":  40,
        "set_pieces_median":  32,
        "set_pieces_volume":  19,
        "benefit":  12.5
    },
    {
        "name":  "Corvas Set",
        "set_median":  40,
        "set_volume":  7,
        "set_max_price":  40,
        "set_min_price":  25,
        "set_pieces_median":  30,
        "set_pieces_volume":  33,
        "benefit":  10
    },
    {
        "name":  "Rathbone Set",
        "set_median":  40,
        "set_volume":  1,
        "set_max_price":  40,
        "set_min_price":  40,
        "set_pieces_median":  23.5,
        "set_pieces_volume":  17,
        "benefit":  16.5
    },
    {
        "name":  "Wyrm Prime Set",
        "set_median":  77,
        "set_volume":  33,
        "set_max_price":  80,
        "set_min_price":  74,
        "set_pieces_median":  65,
        "set_pieces_volume":  64,
        "benefit":  12
    },
    {
        "name":  "Glaive Prime Set",
        "set_median":  80.0,
        "set_volume":  40,
        "set_max_price":  80,
        "set_min_price":  78,
        "set_pieces_median":  61,
        "set_pieces_volume":  222,
        "benefit":  19.0
    },
    {
        "name":  "Scindo Prime Set",
        "set_median":  30.0,
        "set_volume":  8,
        "set_max_price":  30,
        "set_min_price":  29,
        "set_pieces_median":  26.5,
        "set_pieces_volume":  19,
        "benefit":  3.5
    },
    {
        "name":  "Akstiletto Prime Set",
        "set_median":  119,
        "set_volume":  9,
        "set_max_price":  125,
        "set_min_price":  110,
        "set_pieces_median":  78.5,
        "set_pieces_volume":  50,
        "benefit":  40.5
    },
    {
        "name":  "Stropha Set",
        "set_median":  20,
        "set_volume":  12,
        "set_max_price":  25,
        "set_min_price":  15,
        "set_pieces_median":  16,
        "set_pieces_volume":  23,
        "benefit":  4
    },
    {
        "name":  "Velox Set",
        "set_median":  10,
        "set_volume":  9,
        "set_max_price":  12,
        "set_min_price":  5,
        "set_pieces_median":  12,
        "set_pieces_volume":  20,
        "benefit":  -2
    },
    {
        "name":  "Stahlta Set",
        "set_median":  20,
        "set_volume":  16,
        "set_max_price":  30,
        "set_min_price":  10,
        "set_pieces_median":  17,
        "set_pieces_volume":  28,
        "benefit":  3
    },
    {
        "name":  "Inaros Prime Set",
        "set_median":  50.0,
        "set_volume":  57,
        "set_max_price":  55,
        "set_min_price":  45,
        "set_pieces_median":  41.5,
        "set_pieces_volume":  194,
        "benefit":  8.5
    },
    {
        "name":  "Karyst Prime Set",
        "set_median":  25,
        "set_volume":  27,
        "set_max_price":  30,
        "set_min_price":  20,
        "set_pieces_median":  24,
        "set_pieces_volume":  52,
        "benefit":  1
    },
    {
        "name":  "Panthera Prime Set",
        "set_median":  50.0,
        "set_volume":  14,
        "set_max_price":  50,
        "set_min_price":  48,
        "set_pieces_median":  35,
        "set_pieces_volume":  108,
        "benefit":  15.0
    },
    {
        "name":  "Phaedra Set",
        "set_median":  55.0,
        "set_volume":  2,
        "set_max_price":  60,
        "set_min_price":  50,
        "set_pieces_median":  34,
        "set_pieces_volume":  16,
        "benefit":  21.0
    },
    {
        "name":  "Cernos Prime Set",
        "set_median":  64,
        "set_volume":  17,
        "set_max_price":  70,
        "set_min_price":  55,
        "set_pieces_median":  48.5,
        "set_pieces_volume":  50,
        "benefit":  15.5
    },
    {
        "name":  "Valkyr Prime Set",
        "set_median":  80.0,
        "set_volume":  22,
        "set_max_price":  80,
        "set_min_price":  77,
        "set_pieces_median":  71,
        "set_pieces_volume":  116,
        "benefit":  9.0
    },
    {
        "name":  "Imperator Vandal Set",
        "set_median":  40,
        "set_volume":  15,
        "set_max_price":  60,
        "set_min_price":  35,
        "set_pieces_median":  32,
        "set_pieces_volume":  16,
        "benefit":  8
    },
    {
        "name":  "Akbolto Prime Set",
        "set_median":  95,
        "set_volume":  11,
        "set_max_price":  100,
        "set_min_price":  85,
        "set_pieces_median":  78,
        "set_pieces_volume":  59,
        "benefit":  17
    },
    {
        "name":  "Limbo Prime Set",
        "set_median":  90.0,
        "set_volume":  35,
        "set_max_price":  100,
        "set_min_price":  80,
        "set_pieces_median":  72,
        "set_pieces_volume":  94,
        "benefit":  18.0
    },
    {
        "name":  "Gorgon Wraith Set",
        "set_median":  10.0,
        "set_volume":  10,
        "set_max_price":  10,
        "set_min_price":  8,
        "set_pieces_median":  15,
        "set_pieces_volume":  18,
        "benefit":  -5.0
    },
    {
        "name":  "Xiphos Set",
        "set_median":  130,
        "set_volume":  1,
        "set_max_price":  130,
        "set_min_price":  130,
        "set_pieces_median":  165,
        "set_pieces_volume":  6,
        "benefit":  -35
    },
    {
        "name":  "Nikana Prime Set",
        "set_median":  94,
        "set_volume":  30,
        "set_max_price":  100,
        "set_min_price":  80,
        "set_pieces_median":  79,
        "set_pieces_volume":  51,
        "benefit":  15
    },
    {
        "name":  "Cyngas Set",
        "set_median":  32.5,
        "set_volume":  2,
        "set_max_price":  45,
        "set_min_price":  20,
        "set_pieces_median":  34.5,
        "set_pieces_volume":  18,
        "benefit":  -2.0
    },
    {
        "name":  "Broken War Set",
        "set_median":  5.0,
        "set_volume":  7,
        "set_max_price":  5,
        "set_min_price":  3,
        "set_pieces_median":  5,
        "set_pieces_volume":  15,
        "benefit":  0.0
    },
    {
        "name":  "Kaszas Set",
        "set_median":  18,
        "set_volume":  1,
        "set_max_price":  18,
        "set_min_price":  18,
        "set_pieces_median":  18,
        "set_pieces_volume":  14,
        "benefit":  0
    },
    {
        "name":  "Velocitus Set",
        "set_median":  40,
        "set_volume":  3,
        "set_max_price":  50,
        "set_min_price":  35,
        "set_pieces_median":  30,
        "set_pieces_volume":  23,
        "benefit":  10
    },
    {
        "name":  "Fluctus Set",
        "set_median":  40,
        "set_volume":  1,
        "set_max_price":  40,
        "set_min_price":  40,
        "set_pieces_median":  29.5,
        "set_pieces_volume":  26,
        "benefit":  10.5
    },
    {
        "name":  "Dual Decurion Set",
        "set_median":  39.0,
        "set_volume":  5,
        "set_max_price":  40,
        "set_min_price":  39,
        "set_pieces_median":  40,
        "set_pieces_volume":  16,
        "benefit":  -1.0
    },
    {
        "name":  "Spira Prime Set",
        "set_median":  131,
        "set_volume":  11,
        "set_max_price":  145,
        "set_min_price":  125,
        "set_pieces_median":  105,
        "set_pieces_volume":  44,
        "benefit":  26
    },
    {
        "name":  "Sheev Set",
        "set_median":  30,
        "set_volume":  5,
        "set_max_price":  35,
        "set_min_price":  30,
        "set_pieces_median":  34,
        "set_pieces_volume":  6,
        "benefit":  -4
    },
    {
        "name":  "Nami Skyla Prime Set",
        "set_median":  99.5,
        "set_volume":  10,
        "set_max_price":  105,
        "set_min_price":  90,
        "set_pieces_median":  82,
        "set_pieces_volume":  62,
        "benefit":  17.5
    },
    {
        "name":  "Kronen Prime Set",
        "set_median":  115,
        "set_volume":  11,
        "set_max_price":  125,
        "set_min_price":  105,
        "set_pieces_median":  95,
        "set_pieces_volume":  58,
        "benefit":  20
    },
    {
        "name":  "Tiberon Prime Set",
        "set_median":  47,
        "set_volume":  8,
        "set_max_price":  50,
        "set_min_price":  45,
        "set_pieces_median":  39.5,
        "set_pieces_volume":  22,
        "benefit":  7.5
    },
    {
        "name":  "Tipedo Prime Set",
        "set_median":  75,
        "set_volume":  5,
        "set_max_price":  84,
        "set_min_price":  70,
        "set_pieces_median":  57,
        "set_pieces_volume":  21,
        "benefit":  18
    },
    {
        "name":  "Atlas Prime Set",
        "set_median":  65.0,
        "set_volume":  45,
        "set_max_price":  70,
        "set_min_price":  53,
        "set_pieces_median":  58,
        "set_pieces_volume":  89,
        "benefit":  7.0
    },
    {
        "name":  "Tekko Prime Set",
        "set_median":  80,
        "set_volume":  7,
        "set_max_price":  89,
        "set_min_price":  79,
        "set_pieces_median":  56.5,
        "set_pieces_volume":  46,
        "benefit":  23.5
    },
    {
        "name":  "Damaged Necramech Weapon Set",
        "set_median":  10.0,
        "set_volume":  2,
        "set_max_price":  10,
        "set_min_price":  10,
        "set_pieces_median":  null,
        "set_pieces_volume":  null,
        "benefit":  10.0
    },
    {
        "name":  "Damaged Necramech Set",
        "set_median":  10,
        "set_volume":  3,
        "set_max_price":  10,
        "set_min_price":  9,
        "set_pieces_median":  null,
        "set_pieces_volume":  null,
        "benefit":  10
    },
    {
        "name":  "Arum Spinosa Set",
        "set_median":  190,
        "set_volume":  1,
        "set_max_price":  190,
        "set_min_price":  190,
        "set_pieces_median":  105,
        "set_pieces_volume":  34,
        "benefit":  85
    },
    {
        "name":  "Sporothrix Set",
        "set_median":  164.0,
        "set_volume":  10,
        "set_max_price":  200,
        "set_min_price":  100,
        "set_pieces_median":  121,
        "set_pieces_volume":  51,
        "benefit":  43.0
    },
    {
        "name":  "Bonewidow Set",
        "set_median":  80,
        "set_volume":  10,
        "set_max_price":  80,
        "set_min_price":  65,
        "set_pieces_median":  83,
        "set_pieces_volume":  4,
        "benefit":  -3
    },
    {
        "name":  "Cortege Set",
        "set_median":  100,
        "set_volume":  1,
        "set_max_price":  100,
        "set_min_price":  100,
        "set_pieces_median":  55,
        "set_pieces_volume":  1,
        "benefit":  45
    },
    {
        "name":  "Voidrig Set",
        "set_median":  70,
        "set_volume":  49,
        "set_max_price":  70,
        "set_min_price":  68,
        "set_pieces_median":  98,
        "set_pieces_volume":  6,
        "benefit":  -28
    },
    {
        "name":  "Cedo Set",
        "set_median":  24.5,
        "set_volume":  24,
        "set_max_price":  30,
        "set_min_price":  15,
        "set_pieces_median":  49,
        "set_pieces_volume":  11,
        "benefit":  -24.5
    },
    {
        "name":  "Chroma Prime Set",
        "set_median":  79,
        "set_volume":  59,
        "set_max_price":  80,
        "set_min_price":  74,
        "set_pieces_median":  62,
        "set_pieces_volume":  159,
        "benefit":  17
    },
    {
        "name":  "Rubico Prime Set",
        "set_median":  65,
        "set_volume":  48,
        "set_max_price":  70,
        "set_min_price":  55,
        "set_pieces_median":  51,
        "set_pieces_volume":  67,
        "benefit":  14
    },
    {
        "name":  "Banshee Prime Set",
        "set_median":  80,
        "set_volume":  29,
        "set_max_price":  88,
        "set_min_price":  67,
        "set_pieces_median":  69,
        "set_pieces_volume":  90,
        "benefit":  11
    },
    {
        "name":  "Vauban Prime Set",
        "set_median":  119.0,
        "set_volume":  54,
        "set_max_price":  120,
        "set_min_price":  114,
        "set_pieces_median":  97,
        "set_pieces_volume":  125,
        "benefit":  22.0
    },
    {
        "name":  "Burston Prime Set",
        "set_median":  9.0,
        "set_volume":  35,
        "set_max_price":  10,
        "set_min_price":  6,
        "set_pieces_median":  10,
        "set_pieces_volume":  55,
        "benefit":  -1.0
    },
    {
        "name":  "Loki Prime Set",
        "set_median":  84,
        "set_volume":  45,
        "set_max_price":  85,
        "set_min_price":  80,
        "set_pieces_median":  70,
        "set_pieces_volume":  96,
        "benefit":  14
    },
    {
        "name":  "Nova Prime Set",
        "set_median":  110.0,
        "set_volume":  93,
        "set_max_price":  120,
        "set_min_price":  100,
        "set_pieces_median":  103,
        "set_pieces_volume":  149,
        "benefit":  7.0
    },
    {
        "name":  "Nyx Prime Set",
        "set_median":  104,
        "set_volume":  83,
        "set_max_price":  115,
        "set_min_price":  90,
        "set_pieces_median":  87,
        "set_pieces_volume":  183,
        "benefit":  17
    },
    {
        "name":  "Soma Prime Set",
        "set_median":  94.5,
        "set_volume":  21,
        "set_max_price":  100,
        "set_min_price":  80,
        "set_pieces_median":  79.5,
        "set_pieces_volume":  68,
        "benefit":  15.0
    },
    {
        "name":  "Zephyr Prime Set",
        "set_median":  100,
        "set_volume":  46,
        "set_max_price":  103,
        "set_min_price":  97,
        "set_pieces_median":  86,
        "set_pieces_volume":  142,
        "benefit":  14
    },
    {
        "name":  "Ivara Prime Set",
        "set_median":  64,
        "set_volume":  71,
        "set_max_price":  75,
        "set_min_price":  58,
        "set_pieces_median":  54,
        "set_pieces_volume":  129,
        "benefit":  10
    },
    {
        "name":  "Akjagara Prime Set",
        "set_median":  96,
        "set_volume":  9,
        "set_max_price":  100,
        "set_min_price":  90,
        "set_pieces_median":  65.5,
        "set_pieces_volume":  45,
        "benefit":  30.5
    },
    {
        "name":  "Mirage Prime Set",
        "set_median":  99.5,
        "set_volume":  63,
        "set_max_price":  100,
        "set_min_price":  97,
        "set_pieces_median":  81,
        "set_pieces_volume":  171,
        "benefit":  18.5
    },
    {
        "name":  "Gram Prime Set",
        "set_median":  38,
        "set_volume":  21,
        "set_max_price":  40,
        "set_min_price":  35,
        "set_pieces_median":  31.5,
        "set_pieces_volume":  35,
        "benefit":  6.5
    },
    {
        "name":  "Pyrana Prime Set",
        "set_median":  55,
        "set_volume":  19,
        "set_max_price":  60,
        "set_min_price":  45,
        "set_pieces_median":  41,
        "set_pieces_volume":  34,
        "benefit":  14
    },
    {
        "name":  "Equinox Prime Set",
        "set_median":  69.0,
        "set_volume":  39,
        "set_max_price":  70,
        "set_min_price":  65,
        "set_pieces_median":  58,
        "set_pieces_volume":  134,
        "benefit":  11.0
    },
    {
        "name":  "Guandao Prime Set",
        "set_median":  54.0,
        "set_volume":  22,
        "set_max_price":  60,
        "set_min_price":  40,
        "set_pieces_median":  38,
        "set_pieces_volume":  73,
        "benefit":  16.0
    },
    {
        "name":  "Zakti Prime Set",
        "set_median":  35.0,
        "set_volume":  13,
        "set_max_price":  40,
        "set_min_price":  30,
        "set_pieces_median":  27.5,
        "set_pieces_volume":  25,
        "benefit":  7.5
    },
    {
        "name":  "Spectra Vandal Set",
        "set_median":  69.0,
        "set_volume":  12,
        "set_max_price":  80,
        "set_min_price":  50,
        "set_pieces_median":  59.5,
        "set_pieces_volume":  29,
        "benefit":  9.5
    },
    {
        "name":  "Bronco Prime Set",
        "set_median":  10.0,
        "set_volume":  30,
        "set_max_price":  10,
        "set_min_price":  8,
        "set_pieces_median":  7,
        "set_pieces_volume":  38,
        "benefit":  3.0
    },
    {
        "name":  "Pathocyst Set",
        "set_median":  47.5,
        "set_volume":  6,
        "set_max_price":  65,
        "set_min_price":  40,
        "set_pieces_median":  31,
        "set_pieces_volume":  26,
        "benefit":  16.5
    },
    {
        "name":  "Ash Prime Set",
        "set_median":  85,
        "set_volume":  93,
        "set_max_price":  90,
        "set_min_price":  79,
        "set_pieces_median":  63,
        "set_pieces_volume":  352,
        "benefit":  22
    },
    {
        "name":  "Mesa Prime Set",
        "set_median":  70,
        "set_volume":  69,
        "set_max_price":  70,
        "set_min_price":  68,
        "set_pieces_median":  59,
        "set_pieces_volume":  232,
        "benefit":  11
    },
    {
        "name":  "Nekros Prime Set",
        "set_median":  120,
        "set_volume":  78,
        "set_max_price":  130,
        "set_min_price":  110,
        "set_pieces_median":  118,
        "set_pieces_volume":  130,
        "benefit":  2
    },
    {
        "name":  "Galatine Prime Set",
        "set_median":  60,
        "set_volume":  13,
        "set_max_price":  69,
        "set_min_price":  49,
        "set_pieces_median":  43.5,
        "set_pieces_volume":  28,
        "benefit":  16.5
    },
    {
        "name":  "Corinth Prime Set",
        "set_median":  80.0,
        "set_volume":  18,
        "set_max_price":  90,
        "set_min_price":  75,
        "set_pieces_median":  69,
        "set_pieces_volume":  61,
        "benefit":  11.0
    },
    {
        "name":  "Nezha Prime Set",
        "set_median":  79,
        "set_volume":  59,
        "set_max_price":  90,
        "set_min_price":  70,
        "set_pieces_median":  71,
        "set_pieces_volume":  140,
        "benefit":  8
    },
    {
        "name":  "Morgha Set",
        "set_median":  95,
        "set_volume":  1,
        "set_max_price":  95,
        "set_min_price":  95,
        "set_pieces_median":  40,
        "set_pieces_volume":  1,
        "benefit":  55
    },
    {
        "name":  "Pandero Prime Set",
        "set_median":  35.0,
        "set_volume":  10,
        "set_max_price":  40,
        "set_min_price":  30,
        "set_pieces_median":  35.5,
        "set_pieces_volume":  22,
        "benefit":  -0.5
    },
    {
        "name":  "Tenora Prime Set",
        "set_median":  65,
        "set_volume":  14,
        "set_max_price":  70,
        "set_min_price":  52,
        "set_pieces_median":  50,
        "set_pieces_volume":  44,
        "benefit":  15
    },
    {
        "name":  "Octavia Prime Set",
        "set_median":  98.0,
        "set_volume":  80,
        "set_max_price":  100,
        "set_min_price":  90,
        "set_pieces_median":  87,
        "set_pieces_volume":  149,
        "benefit":  11.0
    },
    {
        "name":  "Nautilus Set",
        "set_median":  75.0,
        "set_volume":  2,
        "set_max_price":  90,
        "set_min_price":  60,
        "set_pieces_median":  58.5,
        "set_pieces_volume":  37,
        "benefit":  16.5
    },
    {
        "name":  "Carmine Penta Set",
        "set_median":  80.0,
        "set_volume":  9,
        "set_max_price":  95,
        "set_min_price":  70,
        "set_pieces_median":  51,
        "set_pieces_volume":  54,
        "benefit":  29.0
    },
    {
        "name":  "Athodai Set",
        "set_median":  80,
        "set_volume":  15,
        "set_max_price":  99,
        "set_min_price":  70,
        "set_pieces_median":  54.5,
        "set_pieces_volume":  30,
        "benefit":  25.5
    },
    {
        "name":  "Epitaph Set",
        "set_median":  10,
        "set_volume":  23,
        "set_max_price":  15,
        "set_min_price":  9,
        "set_pieces_median":  14.5,
        "set_pieces_volume":  22,
        "benefit":  -4.5
    },
    {
        "name":  "Volnus Prime Set",
        "set_median":  28,
        "set_volume":  14,
        "set_max_price":  35,
        "set_min_price":  24,
        "set_pieces_median":  28,
        "set_pieces_volume":  23,
        "benefit":  0
    },
    {
        "name":  "Gara Prime Set",
        "set_median":  67.0,
        "set_volume":  67,
        "set_max_price":  75,
        "set_min_price":  55,
        "set_pieces_median":  59,
        "set_pieces_volume":  108,
        "benefit":  8.0
    },
    {
        "name":  "Astilla Prime Set",
        "set_median":  39,
        "set_volume":  19,
        "set_max_price":  40,
        "set_min_price":  35,
        "set_pieces_median":  32,
        "set_pieces_volume":  49,
        "benefit":  7
    },
    {
        "name":  "Meridian Armor Set",
        "set_median":  20,
        "set_volume":  1,
        "set_max_price":  20,
        "set_min_price":  20,
        "set_pieces_median":  0,
        "set_pieces_volume":  0,
        "benefit":  20
    },
    {
        "name":  "Perrin Armor Set",
        "set_median":  49,
        "set_volume":  1,
        "set_max_price":  49,
        "set_min_price":  49,
        "set_pieces_median":  0,
        "set_pieces_volume":  0,
        "benefit":  49
    },
    {
        "name":  "Suda Armor Set",
        "set_median":  70,
        "set_volume":  1,
        "set_max_price":  70,
        "set_min_price":  70,
        "set_pieces_median":  0,
        "set_pieces_volume":  0,
        "benefit":  70
    },
    {
        "name":  "Solaris Armor Set",
        "set_median":  null,
        "set_volume":  null,
        "set_max_price":  null,
        "set_min_price":  null,
        "set_pieces_median":  0,
        "set_pieces_volume":  0,
        "benefit":  0
    },
    {
        "name":  "Lokan Armor Set",
        "set_median":  10,
        "set_volume":  1,
        "set_max_price":  10,
        "set_min_price":  10,
        "set_pieces_median":  0,
        "set_pieces_volume":  0,
        "benefit":  10
    },
    {
        "name":  "Ostron Armor Set",
        "set_median":  100,
        "set_volume":  1,
        "set_max_price":  100,
        "set_min_price":  100,
        "set_pieces_median":  0,
        "set_pieces_volume":  0,
        "benefit":  100
    },
    {
        "name":  "Hexis Armor Set",
        "set_median":  52.5,
        "set_volume":  2,
        "set_max_price":  60,
        "set_min_price":  45,
        "set_pieces_median":  100,
        "set_pieces_volume":  1,
        "benefit":  -47.5
    },
    {
        "name":  "Red Veil Armor Set",
        "set_median":  40,
        "set_volume":  1,
        "set_max_price":  40,
        "set_min_price":  40,
        "set_pieces_median":  0,
        "set_pieces_volume":  0,
        "benefit":  40
    },
    {
        "name":  "Ambassador Set",
        "set_median":  38.0,
        "set_volume":  10,
        "set_max_price":  45,
        "set_min_price":  30,
        "set_pieces_median":  48,
        "set_pieces_volume":  23,
        "benefit":  -10.0
    },
    {
        "name":  "Strun Prime Set",
        "set_median":  50.0,
        "set_volume":  22,
        "set_max_price":  50,
        "set_min_price":  48,
        "set_pieces_median":  38,
        "set_pieces_volume":  49,
        "benefit":  12.0
    },
    {
        "name":  "Magnus Prime Set",
        "set_median":  48.0,
        "set_volume":  63,
        "set_max_price":  50,
        "set_min_price":  43,
        "set_pieces_median":  38.5,
        "set_pieces_volume":  93,
        "benefit":  9.5
    },
    {
        "name":  "Nidus Prime Set",
        "set_median":  80.0,
        "set_volume":  54,
        "set_max_price":  85,
        "set_min_price":  75,
        "set_pieces_median":  70,
        "set_pieces_volume":  102,
        "benefit":  10.0
    },
    {
        "name":  "Ghoulsaw Set",
        "set_median":  10.0,
        "set_volume":  2,
        "set_max_price":  10,
        "set_min_price":  10,
        "set_pieces_median":  0,
        "set_pieces_volume":  0,
        "benefit":  10.0
    },
    {
        "name":  "Knell Prime Set",
        "set_median":  35.0,
        "set_volume":  12,
        "set_max_price":  40,
        "set_min_price":  30,
        "set_pieces_median":  35.5,
        "set_pieces_volume":  31,
        "benefit":  -0.5
    },
    {
        "name":  "Harrow Prime Set",
        "set_median":  59.0,
        "set_volume":  58,
        "set_max_price":  60,
        "set_min_price":  57,
        "set_pieces_median":  50,
        "set_pieces_volume":  129,
        "benefit":  9.0
    },
    {
        "name":  "Scourge Prime Set",
        "set_median":  75,
        "set_volume":  9,
        "set_max_price":  77,
        "set_min_price":  74,
        "set_pieces_median":  57,
        "set_pieces_volume":  53,
        "benefit":  18
    },
    {
        "name":  "Corvas Prime Set",
        "set_median":  40,
        "set_volume":  22,
        "set_max_price":  45,
        "set_min_price":  35,
        "set_pieces_median":  33,
        "set_pieces_volume":  31,
        "benefit":  7
    },
    {
        "name":  "Nagantaka Prime Set",
        "set_median":  30,
        "set_volume":  26,
        "set_max_price":  39,
        "set_min_price":  23,
        "set_pieces_median":  25,
        "set_pieces_volume":  54,
        "benefit":  5
    },
    {
        "name":  "Garuda Prime Set",
        "set_median":  75.0,
        "set_volume":  64,
        "set_max_price":  80,
        "set_min_price":  68,
        "set_pieces_median":  68,
        "set_pieces_volume":  174,
        "benefit":  7.0
    },
    {
        "name":  "Aeolak Set",
        "set_median":  80,
        "set_volume":  9,
        "set_max_price":  100,
        "set_min_price":  70,
        "set_pieces_median":  70,
        "set_pieces_volume":  46,
        "benefit":  10
    },
    {
        "name":  "Hespar Set",
        "set_median":  170,
        "set_volume":  3,
        "set_max_price":  180,
        "set_min_price":  160,
        "set_pieces_median":  145,
        "set_pieces_volume":  46,
        "benefit":  25
    },
    {
        "name":  "Parallax Set",
        "set_median":  10,
        "set_volume":  92,
        "set_max_price":  25,
        "set_min_price":  5,
        "set_pieces_median":  14.5,
        "set_pieces_volume":  80,
        "benefit":  -4.5
    },
    {
        "name":  "Prisma Shade Set",
        "set_median":  50,
        "set_volume":  9,
        "set_max_price":  60,
        "set_min_price":  45,
        "set_pieces_median":  55,
        "set_pieces_volume":  2,
        "benefit":  -5
    },
    {
        "name":  "Dual Keres Prime Set",
        "set_median":  40.0,
        "set_volume":  21,
        "set_max_price":  50,
        "set_min_price":  30,
        "set_pieces_median":  35,
        "set_pieces_volume":  39,
        "benefit":  5.0
    },
    {
        "name":  "Hystrix Prime Set",
        "set_median":  20,
        "set_volume":  9,
        "set_max_price":  21,
        "set_min_price":  20,
        "set_pieces_median":  20,
        "set_pieces_volume":  35,
        "benefit":  0
    },
    {
        "name":  "Khora Prime Set",
        "set_median":  75.0,
        "set_volume":  90,
        "set_max_price":  75,
        "set_min_price":  72,
        "set_pieces_median":  71,
        "set_pieces_volume":  226,
        "benefit":  4.0
    },
    {
        "name":  "Tatsu Prime Set",
        "set_median":  20.0,
        "set_volume":  28,
        "set_max_price":  25,
        "set_min_price":  17,
        "set_pieces_median":  21,
        "set_pieces_volume":  43,
        "benefit":  -1.0
    },
    {
        "name":  "Revenant Prime Set",
        "set_median":  55,
        "set_volume":  186,
        "set_max_price":  65,
        "set_min_price":  45,
        "set_pieces_median":  44,
        "set_pieces_volume":  276,
        "benefit":  11
    },
    {
        "name":  "Phantasma Prime Set",
        "set_median":  50,
        "set_volume":  34,
        "set_max_price":  50,
        "set_min_price":  45,
        "set_pieces_median":  37.5,
        "set_pieces_volume":  62,
        "benefit":  12.5
    },
    {
        "name":  "Perigale Set",
        "set_median":  4.5,
        "set_volume":  4,
        "set_max_price":  5,
        "set_min_price":  4,
        "set_pieces_median":  7,
        "set_pieces_volume":  14,
        "benefit":  -2.5
    },
    {
        "name":  "Sarofang Set",
        "set_median":  3,
        "set_volume":  5,
        "set_max_price":  5,
        "set_min_price":  2,
        "set_pieces_median":  6,
        "set_pieces_volume":  5,
        "benefit":  -3
    },
    {
        "name":  "Baruuk Prime Set",
        "set_median":  50,
        "set_volume":  48,
        "set_max_price":  50,
        "set_min_price":  49,
        "set_pieces_median":  42,
        "set_pieces_volume":  138,
        "benefit":  8
    },
    {
        "name":  "Afuris Prime Set",
        "set_median":  75.0,
        "set_volume":  10,
        "set_max_price":  80,
        "set_min_price":  70,
        "set_pieces_median":  76,
        "set_pieces_volume":  49,
        "benefit":  -1.0
    },
    {
        "name":  "Cobra \u0026 Crane Prime Set",
        "set_median":  19,
        "set_volume":  21,
        "set_max_price":  20,
        "set_min_price":  15,
        "set_pieces_median":  20,
        "set_pieces_volume":  32,
        "benefit":  -1
    },
    {
        "name":  "Steflos Set",
        "set_median":  19.0,
        "set_volume":  4,
        "set_max_price":  25,
        "set_min_price":  15,
        "set_pieces_median":  26,
        "set_pieces_volume":  10,
        "benefit":  -7.0
    },
    {
        "name":  "Corufell Set",
        "set_median":  25,
        "set_volume":  4,
        "set_max_price":  30,
        "set_min_price":  24,
        "set_pieces_median":  23.5,
        "set_pieces_volume":  20,
        "benefit":  1.5
    },
    {
        "name":  "Hildryn Prime Set",
        "set_median":  30,
        "set_volume":  76,
        "set_max_price":  32,
        "set_min_price":  28,
        "set_pieces_median":  34,
        "set_pieces_volume":  97,
        "benefit":  -4
    },
    {
        "name":  "Larkspur Prime Set",
        "set_median":  20,
        "set_volume":  34,
        "set_max_price":  25,
        "set_min_price":  15,
        "set_pieces_median":  22,
        "set_pieces_volume":  45,
        "benefit":  -2
    },
    {
        "name":  "Shade Prime Set",
        "set_median":  25,
        "set_volume":  44,
        "set_max_price":  25,
        "set_min_price":  22,
        "set_pieces_median":  27.5,
        "set_pieces_volume":  105,
        "benefit":  -2.5
    },
    {
        "name":  "Cinta Set",
        "set_median":  65.0,
        "set_volume":  2,
        "set_max_price":  70,
        "set_min_price":  60,
        "set_pieces_median":  42,
        "set_pieces_volume":  39,
        "benefit":  23.0
    },
    {
        "name":  "Rauta Set",
        "set_median":  25,
        "set_volume":  11,
        "set_max_price":  30,
        "set_min_price":  20,
        "set_pieces_median":  36,
        "set_pieces_volume":  4,
        "benefit":  -11
    },
    {
        "name":  "Gunsen Prime Set",
        "set_median":  28,
        "set_volume":  35,
        "set_max_price":  30,
        "set_min_price":  22,
        "set_pieces_median":  25,
        "set_pieces_volume":  72,
        "benefit":  3
    },
    {
        "name":  "Wisp Prime Set",
        "set_median":  40,
        "set_volume":  259,
        "set_max_price":  80,
        "set_min_price":  32,
        "set_pieces_median":  38,
        "set_pieces_volume":  390,
        "benefit":  2
    },
    {
        "name":  "Fulmin Prime Set",
        "set_median":  15,
        "set_volume":  69,
        "set_max_price":  15,
        "set_min_price":  13,
        "set_pieces_median":  17,
        "set_pieces_volume":  118,
        "benefit":  -2
    },
    {
        "name":  "Grendel Prime Set",
        "set_median":  35,
        "set_volume":  105,
        "set_max_price":  45,
        "set_min_price":  25,
        "set_pieces_median":  30,
        "set_pieces_volume":  213,
        "benefit":  5
    },
    {
        "name":  "Masseter Prime Set",
        "set_median":  10,
        "set_volume":  50,
        "set_max_price":  12,
        "set_min_price":  8,
        "set_pieces_median":  11,
        "set_pieces_volume":  111,
        "benefit":  -1
    },
    {
        "name":  "Zylok Prime Set",
        "set_median":  13.0,
        "set_volume":  32,
        "set_max_price":  15,
        "set_min_price":  9,
        "set_pieces_median":  12,
        "set_pieces_volume":  52,
        "benefit":  1.0
    },
    {
        "name":  "Mandonel Set",
        "set_median":  15,
        "set_volume":  17,
        "set_max_price":  15,
        "set_min_price":  14,
        "set_pieces_median":  17,
        "set_pieces_volume":  42,
        "benefit":  -2
    },
    {
        "name":  "Gauss Prime Set",
        "set_median":  30,
        "set_volume":  250,
        "set_max_price":  35,
        "set_min_price":  25,
        "set_pieces_median":  25,
        "set_pieces_volume":  282,
        "benefit":  5
    },
    {
        "name":  "Akarius Prime Set",
        "set_median":  40,
        "set_volume":  93,
        "set_max_price":  45,
        "set_min_price":  35,
        "set_pieces_median":  39,
        "set_pieces_volume":  297,
        "benefit":  1
    },
    {
        "name":  "Acceltra Prime Set",
        "set_median":  30,
        "set_volume":  87,
        "set_max_price":  30,
        "set_min_price":  28,
        "set_pieces_median":  26,
        "set_pieces_volume":  248,
        "benefit":  4
    },
    {
        "name":  "Protea Prime Set",
        "set_median":  40,
        "set_volume":  153,
        "set_max_price":  45,
        "set_min_price":  35,
        "set_pieces_median":  40.5,
        "set_pieces_volume":  243,
        "benefit":  -0.5
    },
    {
        "name":  "Velox Prime Set",
        "set_median":  15.0,
        "set_volume":  30,
        "set_max_price":  20,
        "set_min_price":  10,
        "set_pieces_median":  15,
        "set_pieces_volume":  71,
        "benefit":  0.0
    },
    {
        "name":  "Okina Prime Set",
        "set_median":  35,
        "set_volume":  40,
        "set_max_price":  37,
        "set_min_price":  33,
        "set_pieces_median":  27,
        "set_pieces_volume":  128,
        "benefit":  8
    },
    {
        "name":  "Akmagnus Prime Set",
        "set_median":  45.0,
        "set_volume":  38,
        "set_max_price":  50,
        "set_min_price":  40,
        "set_pieces_median":  30,
        "set_pieces_volume":  64,
        "benefit":  15.0
    },
    {
        "name":  "Sevagoth Prime Set",
        "set_median":  34.0,
        "set_volume":  232,
        "set_max_price":  45,
        "set_min_price":  25,
        "set_pieces_median":  29,
        "set_pieces_volume":  383,
        "benefit":  5.0
    },
    {
        "name":  "Epitaph Prime Set",
        "set_median":  28.0,
        "set_volume":  112,
        "set_max_price":  30,
        "set_min_price":  22,
        "set_pieces_median":  20,
        "set_pieces_volume":  114,
        "benefit":  8.0
    },
    {
        "name":  "Nautilus Prime Set",
        "set_median":  40,
        "set_volume":  111,
        "set_max_price":  42,
        "set_min_price":  38,
        "set_pieces_median":  32,
        "set_pieces_volume":  307,
        "benefit":  8
    },
    {
        "name":  "Xaku Prime Set",
        "set_median":  50,
        "set_volume":  161,
        "set_max_price":  52,
        "set_min_price":  48,
        "set_pieces_median":  40,
        "set_pieces_volume":  511,
        "benefit":  10
    },
    {
        "name":  "Trumna Prime Set",
        "set_median":  40.0,
        "set_volume":  119,
        "set_max_price":  60,
        "set_min_price":  28,
        "set_pieces_median":  31,
        "set_pieces_volume":  243,
        "benefit":  9.0
    },
    {
        "name":  "Quassus Prime Set",
        "set_median":  49,
        "set_volume":  63,
        "set_max_price":  60,
        "set_min_price":  40,
        "set_pieces_median":  36,
        "set_pieces_volume":  215,
        "benefit":  13
    },
    {
        "name":  "Reconifex Set",
        "set_median":  19.0,
        "set_volume":  2,
        "set_max_price":  23,
        "set_min_price":  15,
        "set_pieces_median":  25.5,
        "set_pieces_volume":  6,
        "benefit":  -6.5
    },
    {
        "name":  "Vesper 77 Set",
        "set_median":  24.5,
        "set_volume":  8,
        "set_max_price":  30,
        "set_min_price":  20,
        "set_pieces_median":  16,
        "set_pieces_volume":  5,
        "benefit":  8.5
    },
    {
        "name":  "Cedo Prime Set",
        "set_median":  78,
        "set_volume":  202,
        "set_max_price":  85,
        "set_min_price":  70,
        "set_pieces_median":  58,
        "set_pieces_volume":  620,
        "benefit":  20
    },
    {
        "name":  "Dual Zoren Prime Set",
        "set_median":  100.0,
        "set_volume":  85,
        "set_max_price":  114,
        "set_min_price":  89,
        "set_pieces_median":  82,
        "set_pieces_volume":  334,
        "benefit":  18.0
    },
    {
        "name":  "Lavos Prime Set",
        "set_median":  75,
        "set_volume":  371,
        "set_max_price":  89,
        "set_min_price":  61,
        "set_pieces_median":  56,
        "set_pieces_volume":  893,
        "benefit":  19
    }
]
